{
    "HeadComp": {
        "title": "Contact Us - Connect with MSG91 Singapore!",
        "description": "Have a question or need support? Contact us via phone, chat, or email for a prompt response."
    },
    "ContactUsComp": {
        "heading": "Contact Us",
        "subheading": "Choose the best way to reach out, whether for sales inquiries or technical assistance.",
        "cards": [
            {
                "key": "sales",
                "heading": "Sales",
                "email": "sales@msg91.com",
                "phone": [
                    {
                        "number": "+65 31595004",
                        "whatsapp": true,
                        "call": true
                    }
                ]
            },
            {
                "key": "support",
                "heading": "Support",
                "email": "support@msg91.com",
                "phone": [
                    {
                        "number": "07316914364",
                        "whatsapp": true,
                        "call": true
                    }
                ]
            },
            {
                "key": "chat",
                "heading": "Chat",
                "widgetToken": "8e51b"
            }
        ]
    }
}